[
  {
    "代码": "600356",
    "名称": "恒丰纸业",
    "最新价": 10.13,
    "涨跌幅": 0.4,
    "成交量": 38353.0,
    "成交额": 38628825.0,
    "最高": 10.15,
    "最低": 10.0,
    "今开": 10.04,
    "昨收": 10.09,
    "总市值_x": 3338204786.0,
    "流通市值_x": 3026148859.0,
    "换手率": 1.28,
    "净利润同比增长率": 70.72,
    "市盈率": 14.67,
    "市净率": 1.28,
    "市销率": 0.6,
    "总市值_y": 3338204786.0,
    "流通市值_y": 3026148859.0,
    "综合评分": 28.2
  },
  {
    "代码": "001218",
    "名称": "丽臣实业",
    "最新价": 26.95,
    "涨跌幅": -1.32,
    "成交量": 34161.0,
    "成交额": 92766462.56,
    "最高": 27.79,
    "最低": 26.71,
    "今开": 27.4,
    "昨收": 27.31,
    "总市值_x": 3508304107.0,
    "流通市值_x": 3181748532.0,
    "换手率": 2.89,
    "净利润同比增长率": 47.99,
    "市盈率": 11.36,
    "市净率": 2.89,
    "市销率": -0.07,
    "总市值_y": 3508304107.0,
    "流通市值_y": 3181748532.0,
    "综合评分": 28.2
  },
  {
    "代码": "603900",
    "名称": "莱绅通灵",
    "最新价": 7.9,
    "涨跌幅": 0.64,
    "成交量": 48911.0,
    "成交额": 38659078.0,
    "最高": 7.94,
    "最低": 7.84,
    "今开": 7.88,
    "昨收": 7.85,
    "总市值_x": 2709414336.0,
    "流通市值_x": 2707518336.0,
    "换手率": 1.43,
    "净利润同比增长率": 132.4100554343,
    "市盈率": 12.66,
    "市净率": 1.43,
    "市销率": -0.13,
    "总市值_y": 2709414336.0,
    "流通市值_y": 2707518336.0,
    "综合评分": 28.2
  },
  {
    "代码": "000692",
    "名称": "惠天热电",
    "最新价": 5.16,
    "涨跌幅": 0.19,
    "成交量": 159473.0,
    "成交额": 81913852.0,
    "最高": 5.22,
    "最低": 5.08,
    "今开": 5.12,
    "昨收": 5.15,
    "总市值_x": 2749418156.0,
    "流通市值_x": 2749418156.0,
    "换手率": 2.99,
    "净利润同比增长率": 83.63,
    "市盈率": 13.94,
    "市净率": 2.99,
    "市销率": 0.19,
    "总市值_y": 2749418156.0,
    "流通市值_y": 2749418156.0,
    "综合评分": 28.2
  },
  {
    "代码": "600738",
    "名称": "丽尚国潮",
    "最新价": 4.76,
    "涨跌幅": 0.85,
    "成交量": 37457.0,
    "成交额": 17767206.0,
    "最高": 4.76,
    "最低": 4.71,
    "今开": 4.72,
    "昨收": 4.72,
    "总市值_x": 3623955723.0,
    "流通市值_x": 3620771093.0,
    "换手率": 0.49,
    "净利润同比增长率": 126.02,
    "市盈率": 14.76,
    "市净率": 0.49,
    "市销率": 0.21,
    "总市值_y": 3623955723.0,
    "流通市值_y": 3620771093.0,
    "综合评分": 28.2
  },
  {
    "代码": "605259",
    "名称": "绿田机械",
    "最新价": 19.66,
    "涨跌幅": -0.51,
    "成交量": 7494.0,
    "成交额": 14719142.0,
    "最高": 19.88,
    "最低": 19.55,
    "今开": 19.87,
    "昨收": 19.76,
    "总市值_x": 3390956800.0,
    "流通市值_x": 3390956800.0,
    "换手率": 0.43,
    "净利润同比增长率": 31.95,
    "市盈率": 18.86,
    "市净率": 0.43,
    "市销率": 0.05,
    "总市值_y": 3390956800.0,
    "流通市值_y": 3390956800.0,
    "综合评分": 27.8
  },
  {
    "代码": "300452",
    "名称": "山河药辅",
    "最新价": 14.01,
    "涨跌幅": -0.43,
    "成交量": 18212.0,
    "成交额": 25532409.75,
    "最高": 14.07,
    "最低": 13.97,
    "今开": 14.04,
    "昨收": 14.07,
    "总市值_x": 3284702557.0,
    "流通市值_x": 2782807645.0,
    "换手率": 0.92,
    "净利润同比增长率": 47.84,
    "市盈率": 17.45,
    "市净率": 0.92,
    "市销率": 0.0,
    "总市值_y": 3284702557.0,
    "流通市值_y": 2782807645.0,
    "综合评分": 27.8
  },
  {
    "代码": "002286",
    "名称": "保龄宝",
    "最新价": 10.21,
    "涨跌幅": 1.49,
    "成交量": 49359.0,
    "成交额": 50147319.17,
    "最高": 10.24,
    "最低": 10.02,
    "今开": 10.06,
    "昨收": 10.06,
    "总市值_x": 3885592950.0,
    "流通市值_x": 3774530489.0,
    "换手率": 1.34,
    "净利润同比增长率": 35.5,
    "市盈率": 17.94,
    "市净率": 1.34,
    "市销率": -0.1,
    "总市值_y": 3885592950.0,
    "流通市值_y": 3774530489.0,
    "综合评分": 27.8
  },
  {
    "代码": "001395",
    "名称": "亚联机械",
    "最新价": 40.07,
    "涨跌幅": -0.17,
    "成交量": 4389.0,
    "成交额": 17581034.0,
    "最高": 40.22,
    "最低": 39.81,
    "今开": 40.01,
    "昨收": 40.14,
    "总市值_x": 3495706800.0,
    "流通市值_x": 1878882300.0,
    "换手率": 0.94,
    "净利润同比增长率": 20.93,
    "市盈率": 18.58,
    "市净率": 0.94,
    "市销率": -0.02,
    "总市值_y": 3495706800.0,
    "流通市值_y": 1878882300.0,
    "综合评分": 27.8
  },
  {
    "代码": "002748",
    "名称": "世龙实业",
    "最新价": 12.7,
    "涨跌幅": -1.47,
    "成交量": 25535.0,
    "成交额": 32638371.0,
    "最高": 12.9,
    "最低": 12.69,
    "今开": 12.81,
    "昨收": 12.89,
    "总市值_x": 3048000000.0,
    "流通市值_x": 3048000000.0,
    "换手率": 1.06,
    "净利润同比增长率": 120.12,
    "市盈率": 19.8,
    "市净率": 1.06,
    "市销率": 0.0,
    "总市值_y": 3048000000.0,
    "流通市值_y": 3048000000.0,
    "综合评分": 27.8
  },
  {
    "代码": "603080",
    "名称": "新疆火炬",
    "最新价": 21.76,
    "涨跌幅": 0.83,
    "成交量": 12441.0,
    "成交额": 27044557.0,
    "最高": 21.85,
    "最低": 21.58,
    "今开": 21.6,
    "昨收": 21.58,
    "总市值_x": 3079040000.0,
    "流通市值_x": 3079040000.0,
    "换手率": 0.88,
    "净利润同比增长率": 34.43,
    "市盈率": 17.06,
    "市净率": 0.88,
    "市销率": -0.18,
    "总市值_y": 3079040000.0,
    "流通市值_y": 3079040000.0,
    "综合评分": 27.8
  },
  {
    "代码": "002942",
    "名称": "新农股份",
    "最新价": 19.7,
    "涨跌幅": 0.0,
    "成交量": 8841.0,
    "成交额": 17372131.9,
    "最高": 19.78,
    "最低": 19.5,
    "今开": 19.74,
    "昨收": 19.7,
    "总市值_x": 3070401221.0,
    "流通市值_x": 2733534235.0,
    "换手率": 0.64,
    "净利润同比增长率": 65.27,
    "市盈率": 16.65,
    "市净率": 0.64,
    "市销率": 0.0,
    "总市值_y": 3070401221.0,
    "流通市值_y": 2733534235.0,
    "综合评分": 27.8
  },
  {
    "代码": "603856",
    "名称": "东宏股份",
    "最新价": 12.91,
    "涨跌幅": -0.15,
    "成交量": 21180.0,
    "成交额": 27213940.0,
    "最高": 12.92,
    "最低": 12.77,
    "今开": 12.9,
    "昨收": 12.93,
    "总市值_x": 3641343735.0,
    "流通市值_x": 3641343735.0,
    "换手率": 0.75,
    "净利润同比增长率": 47.35,
    "市盈率": 20.41,
    "市净率": 0.75,
    "市销率": 0.31,
    "总市值_y": 3641343735.0,
    "流通市值_y": 3641343735.0,
    "综合评分": 27.4
  },
  {
    "代码": "001256",
    "名称": "炜冈科技",
    "最新价": 25.29,
    "涨跌幅": 0.6,
    "成交量": 11242.0,
    "成交额": 28311543.05,
    "最高": 25.33,
    "最低": 24.92,
    "今开": 25.14,
    "昨收": 25.14,
    "总市值_x": 3606671592.0,
    "流通市值_x": 2703818592.0,
    "换手率": 1.05,
    "净利润同比增长率": 47.49,
    "市盈率": 23.98,
    "市净率": 1.05,
    "市销率": 0.08,
    "总市值_y": 3606671592.0,
    "流通市值_y": 2703818592.0,
    "综合评分": 27.4
  },
  {
    "代码": "603566",
    "名称": "普莱柯",
    "最新价": 11.66,
    "涨跌幅": -0.09,
    "成交量": 19134.0,
    "成交额": 22248255.0,
    "最高": 11.7,
    "最低": 11.6,
    "今开": 11.63,
    "昨收": 11.67,
    "总市值_x": 4035086103.0,
    "流通市值_x": 4035086103.0,
    "换手率": 0.55,
    "净利润同比增长率": 99.33,
    "市盈率": 24.76,
    "市净率": 0.55,
    "市销率": 0.17,
    "总市值_y": 4035086103.0,
    "流通市值_y": 4035086103.0,
    "综合评分": 27.4
  },
  {
    "代码": "003017",
    "名称": "大洋生物",
    "最新价": 32.01,
    "涨跌幅": 0.16,
    "成交量": 15539.0,
    "成交额": 49813750.0,
    "最高": 32.32,
    "最低": 31.83,
    "今开": 31.93,
    "昨收": 31.96,
    "总市值_x": 2688840000.0,
    "流通市值_x": 2217908496.0,
    "换手率": 2.24,
    "净利润同比增长率": 56.64,
    "市盈率": 21.77,
    "市净率": 2.24,
    "市销率": -0.09,
    "总市值_y": 2688840000.0,
    "流通市值_y": 2217908496.0,
    "综合评分": 27.4
  },
  {
    "代码": "301283",
    "名称": "聚胶股份",
    "最新价": 48.63,
    "涨跌幅": 0.1,
    "成交量": 7416.0,
    "成交额": 36013523.75,
    "最高": 49.0,
    "最低": 48.13,
    "今开": 48.54,
    "昨收": 48.58,
    "总市值_x": 3910718684.0,
    "流通市值_x": 3077153216.0,
    "换手率": 1.17,
    "净利润同比增长率": 144.63,
    "市盈率": 24.6,
    "市净率": 1.17,
    "市销率": 0.23,
    "总市值_y": 3910718684.0,
    "流通市值_y": 3077153216.0,
    "综合评分": 27.4
  },
  {
    "代码": "603238",
    "名称": "诺邦股份",
    "最新价": 15.91,
    "涨跌幅": 0.32,
    "成交量": 11136.0,
    "成交额": 17659250.0,
    "最高": 15.97,
    "最低": 15.76,
    "今开": 15.97,
    "昨收": 15.86,
    "总市值_x": 2824168190.0,
    "流通市值_x": 2824168190.0,
    "换手率": 0.63,
    "净利润同比增长率": 23.2,
    "市盈率": 22.75,
    "市净率": 0.63,
    "市销率": 0.06,
    "总市值_y": 2824168190.0,
    "流通市值_y": 2824168190.0,
    "综合评分": 27.4
  },
  {
    "代码": "603500",
    "名称": "祥和实业",
    "最新价": 10.44,
    "涨跌幅": 0.68,
    "成交量": 34183.0,
    "成交额": 35557686.0,
    "最高": 10.47,
    "最低": 10.29,
    "今开": 10.34,
    "昨收": 10.37,
    "总市值_x": 3474330168.0,
    "流通市值_x": 3472438680.0,
    "换手率": 1.03,
    "净利润同比增长率": 78.31,
    "市盈率": 22.09,
    "市净率": 1.03,
    "市销率": -0.1,
    "总市值_y": 3474330168.0,
    "流通市值_y": 3472438680.0,
    "综合评分": 27.4
  },
  {
    "代码": "001230",
    "名称": "劲旅环境",
    "最新价": 28.07,
    "涨跌幅": 0.79,
    "成交量": 11297.0,
    "成交额": 31587070.22,
    "最高": 28.19,
    "最低": 27.6,
    "今开": 27.77,
    "昨收": 27.85,
    "总市值_x": 3764918420.0,
    "流通市值_x": 2205074499.0,
    "换手率": 1.44,
    "净利润同比增长率": 20.33,
    "市盈率": 22.23,
    "市净率": 1.44,
    "市销率": 0.04,
    "总市值_y": 3764918420.0,
    "流通市值_y": 2205074499.0,
    "综合评分": 27.4
  },
  {
    "代码": "000803",
    "名称": "山高环能",
    "最新价": 8.58,
    "涨跌幅": -2.5,
    "成交量": 77691.0,
    "成交额": 67214191.97,
    "最高": 8.78,
    "最低": 8.55,
    "今开": 8.78,
    "昨收": 8.8,
    "总市值_x": 4000820993.0,
    "流通市值_x": 3944979152.0,
    "换手率": 1.69,
    "净利润同比增长率": 132.39,
    "市盈率": 22.87,
    "市净率": 1.69,
    "市销率": 0.12,
    "总市值_y": 4000820993.0,
    "流通市值_y": 3944979152.0,
    "综合评分": 27.4
  },
  {
    "代码": "001228",
    "名称": "永泰运",
    "最新价": 30.57,
    "涨跌幅": -1.13,
    "成交量": 9592.0,
    "成交额": 29503274.5,
    "最高": 31.14,
    "最低": 30.42,
    "今开": 30.77,
    "昨收": 30.92,
    "总市值_x": 3175141097.0,
    "流通市值_x": 2441461097.0,
    "换手率": 1.2,
    "净利润同比增长率": 21.73,
    "市盈率": 22.97,
    "市净率": 1.2,
    "市销率": 0.07,
    "总市值_y": 3175141097.0,
    "流通市值_y": 2441461097.0,
    "综合评分": 27.4
  },
  {
    "代码": "300562",
    "名称": "乐心医疗",
    "最新价": 14.49,
    "涨跌幅": 0.35,
    "成交量": 38789.0,
    "成交额": 56276904.0,
    "最高": 14.58,
    "最低": 14.36,
    "今开": 14.4,
    "昨收": 14.44,
    "总市值_x": 3167712339.0,
    "流通市值_x": 2361240163.0,
    "换手率": 2.38,
    "净利润同比增长率": 33.63,
    "市盈率": 24.69,
    "市净率": 2.38,
    "市销率": -0.21,
    "总市值_y": 3167712339.0,
    "流通市值_y": 2361240163.0,
    "综合评分": 27.4
  },
  {
    "代码": "605033",
    "名称": "美邦股份",
    "最新价": 23.28,
    "涨跌幅": 0.34,
    "成交量": 13839.0,
    "成交额": 32103037.0,
    "最高": 23.35,
    "最低": 23.06,
    "今开": 23.2,
    "昨收": 23.2,
    "总市值_x": 3147456000.0,
    "流通市值_x": 3147456000.0,
    "换手率": 1.02,
    "净利润同比增长率": 32.03,
    "市盈率": 22.09,
    "市净率": 1.02,
    "市销率": -0.04,
    "总市值_y": 3147456000.0,
    "流通市值_y": 3147456000.0,
    "综合评分": 27.4
  },
  {
    "代码": "603787",
    "名称": "新日股份",
    "最新价": 12.09,
    "涨跌幅": 1.17,
    "成交量": 38195.0,
    "成交额": 45725202.0,
    "最高": 12.11,
    "最低": 11.85,
    "今开": 11.95,
    "昨收": 11.95,
    "总市值_x": 2782438421.0,
    "流通市值_x": 2782438421.0,
    "换手率": 1.66,
    "净利润同比增长率": 97.47,
    "市盈率": 27.63,
    "市净率": 1.66,
    "市销率": 0.0,
    "总市值_y": 2782438421.0,
    "流通市值_y": 2782438421.0,
    "综合评分": 27.0
  },
  {
    "代码": "300515",
    "名称": "三德科技",
    "最新价": 17.06,
    "涨跌幅": -0.29,
    "成交量": 17933.0,
    "成交额": 30638720.0,
    "最高": 17.28,
    "最低": 16.97,
    "今开": 17.28,
    "昨收": 17.11,
    "总市值_x": 3510171770.0,
    "流通市值_x": 3441987642.0,
    "换手率": 0.89,
    "净利润同比增长率": 28.2,
    "市盈率": 26.49,
    "市净率": 0.89,
    "市销率": 0.12,
    "总市值_y": 3510171770.0,
    "流通市值_y": 3441987642.0,
    "综合评分": 27.0
  },
  {
    "代码": "603231",
    "名称": "索宝蛋白",
    "最新价": 17.33,
    "涨跌幅": 0.81,
    "成交量": 11952.0,
    "成交额": 20675109.0,
    "最高": 17.36,
    "最低": 17.2,
    "今开": 17.2,
    "昨收": 17.19,
    "总市值_x": 3317986290.0,
    "流通市值_x": 1841589468.0,
    "换手率": 1.12,
    "净利润同比增长率": 56.56,
    "市盈率": 26.1,
    "市净率": 1.12,
    "市销率": 0.0,
    "总市值_y": 3317986290.0,
    "流通市值_y": 1841589468.0,
    "综合评分": 27.0
  },
  {
    "代码": "300824",
    "名称": "北鼎股份",
    "最新价": 10.12,
    "涨跌幅": 0.4,
    "成交量": 17877.0,
    "成交额": 18015821.5,
    "最高": 10.15,
    "最低": 10.0,
    "今开": 10.0,
    "昨收": 10.08,
    "总市值_x": 3302577822.0,
    "流通市值_x": 3203084307.0,
    "换手率": 0.56,
    "净利润同比增长率": 63.35,
    "市盈率": 25.2,
    "市净率": 0.56,
    "市销率": -0.1,
    "总市值_y": 3302577822.0,
    "流通市值_y": 3203084307.0,
    "综合评分": 27.0
  },
  {
    "代码": "600455",
    "名称": "博通股份",
    "最新价": 29.22,
    "涨跌幅": 0.62,
    "成交量": 12694.0,
    "成交额": 37126322.0,
    "最高": 29.48,
    "最低": 29.06,
    "今开": 29.38,
    "昨收": 29.04,
    "总市值_x": 1825022760.0,
    "流通市值_x": 1825022760.0,
    "换手率": 2.03,
    "净利润同比增长率": 36.43,
    "市盈率": 26.8,
    "市净率": 2.03,
    "市销率": 0.07,
    "总市值_y": 1825022760.0,
    "流通市值_y": 1825022760.0,
    "综合评分": 27.0
  },
  {
    "代码": "300534",
    "名称": "陇神戎发",
    "最新价": 9.28,
    "涨跌幅": 0.32,
    "成交量": 31082.0,
    "成交额": 28858507.0,
    "最高": 9.33,
    "最低": 9.25,
    "今开": 9.28,
    "昨收": 9.25,
    "总市值_x": 2815041600.0,
    "流通市值_x": 2803037809.0,
    "换手率": 1.03,
    "净利润同比增长率": 79.56,
    "市盈率": 28.54,
    "市净率": 1.03,
    "市销率": -0.22,
    "总市值_y": 2815041600.0,
    "流通市值_y": 2803037809.0,
    "综合评分": 27.0
  }
]